wagtailadminfontawesome/__init__.py
wagtailadminfontawesome/apps.py
wagtailadminfontawesome/wagtail_hooks.py
wagtailadminfontawesome/static/wagtailadminfontawesome/wagtail-admin-fontawesome.scss
wagtailadminfontawesome/static/wagtailadminfontawesome/css/wagtail-admin-fontawesome.min.css
wagtailadminfontawesome/static/wagtailadminfontawesome/css/.maps/main.min.css.map
wagtailadminfontawesome/static/wagtailadminfontawesome/css/.maps/wagtail-admin-fontawesome.min.css.map
wagtailadminfontawesome/static/wagtailadminfontawesome/webfonts/fa-brands-400.eot
wagtailadminfontawesome/static/wagtailadminfontawesome/webfonts/fa-brands-400.svg
wagtailadminfontawesome/static/wagtailadminfontawesome/webfonts/fa-brands-400.ttf
wagtailadminfontawesome/static/wagtailadminfontawesome/webfonts/fa-brands-400.woff
wagtailadminfontawesome/static/wagtailadminfontawesome/webfonts/fa-brands-400.woff2
wagtailadminfontawesome/static/wagtailadminfontawesome/webfonts/fa-regular-400.eot
wagtailadminfontawesome/static/wagtailadminfontawesome/webfonts/fa-regular-400.svg
wagtailadminfontawesome/static/wagtailadminfontawesome/webfonts/fa-regular-400.ttf
wagtailadminfontawesome/static/wagtailadminfontawesome/webfonts/fa-regular-400.woff
wagtailadminfontawesome/static/wagtailadminfontawesome/webfonts/fa-regular-400.woff2
wagtailadminfontawesome/static/wagtailadminfontawesome/webfonts/fa-solid-900.eot
wagtailadminfontawesome/static/wagtailadminfontawesome/webfonts/fa-solid-900.svg
wagtailadminfontawesome/static/wagtailadminfontawesome/webfonts/fa-solid-900.ttf
wagtailadminfontawesome/static/wagtailadminfontawesome/webfonts/fa-solid-900.woff
wagtailadminfontawesome/static/wagtailadminfontawesome/webfonts/fa-solid-900.woff2
wagtailadminfontawesome-1.0.0.dist-info/LICENSE
wagtailadminfontawesome-1.0.0.dist-info/METADATA
wagtailadminfontawesome-1.0.0.dist-info/WHEEL
wagtailadminfontawesome-1.0.0.dist-info/top_level.txt
wagtailadminfontawesome-1.0.0.dist-info/RECORD
