Metadata-Version: 2.1
Name: wagtailadminfontawesome
Version: 1.0.0
Summary: Add Fontawesome5 to Wagtail project's admin
Home-page: https://github.com/lorenzomonte-it/wagtail-admin-fontawesome
Author: Lorenzo
License: MIT
Project-URL: Homepage, https://github.com/lorenzomonte-it/wagtail-admin-fontawesome
Platform: UNKNOWN
Classifier: License :: OSI Approved :: MIT License
Classifier: Operating System :: OS Independent
Classifier: Programming Language :: Python
Classifier: Framework :: Django
Classifier: Framework :: Wagtail
Requires-Dist: Django (>=3.1.7)
Requires-Dist: Wagtail (>=2.12.2)
